tauntaun_live_editor/__init__.py
tauntaun_live_editor/__main__.py
tauntaun_live_editor/camp.py
tauntaun_live_editor/config.py
tauntaun_live_editor/coord.py
tauntaun_live_editor/namegen.py
tauntaun_live_editor/sessions.py
tauntaun_live_editor/static_data.py
tauntaun_live_editor/util.py
tauntaun_live_editor/data/Missions/default.miz
tauntaun_live_editor/data/client/asset-manifest.json
tauntaun_live_editor/data/client/bullseye.png
tauntaun_live_editor/data/client/favicon.ico
tauntaun_live_editor/data/client/index.html
tauntaun_live_editor/data/client/logo192.png
tauntaun_live_editor/data/client/logo512.png
tauntaun_live_editor/data/client/manifest.json
tauntaun_live_editor/data/client/robots.txt
tauntaun_live_editor/data/client/static/css/main.7a307b3f.chunk.css
tauntaun_live_editor/data/client/static/css/main.7a307b3f.chunk.css.map
tauntaun_live_editor/data/client/static/js/2.ca150401.chunk.js
tauntaun_live_editor/data/client/static/js/2.ca150401.chunk.js.LICENSE.txt
tauntaun_live_editor/data/client/static/js/2.ca150401.chunk.js.map
tauntaun_live_editor/data/client/static/js/main.47ec07b3.chunk.js
tauntaun_live_editor/data/client/static/js/main.47ec07b3.chunk.js.map
tauntaun_live_editor/data/client/static/js/runtime-main.57d44ea6.js
tauntaun_live_editor/data/client/static/js/runtime-main.57d44ea6.js.map
tauntaun_live_editor/dcs/.git
tauntaun_live_editor/dcs/.gitignore
tauntaun_live_editor/dcs/LICENSE.txt
tauntaun_live_editor/dcs/Manifest.in
tauntaun_live_editor/dcs/README.md
tauntaun_live_editor/dcs/requirements.txt
tauntaun_live_editor/dcs/setup.py
tauntaun_live_editor/dcs/.github/workflows/pythonpackage.yml
tauntaun_live_editor/dcs/dcs/__init__.py
tauntaun_live_editor/dcs/dcs/action.py
tauntaun_live_editor/dcs/dcs/coalition.py
tauntaun_live_editor/dcs/dcs/condition.py
tauntaun_live_editor/dcs/dcs/countries.py
tauntaun_live_editor/dcs/dcs/country.py
tauntaun_live_editor/dcs/dcs/flyingunit.py
tauntaun_live_editor/dcs/dcs/forcedoptions.py
tauntaun_live_editor-0.2.2.dist-info/COPYING
tauntaun_live_editor-0.2.2.dist-info/METADATA
tauntaun_live_editor-0.2.2.dist-info/WHEEL
tauntaun_live_editor-0.2.2.dist-info/entry_points.txt
tauntaun_live_editor-0.2.2.dist-info/top_level.txt
tauntaun_live_editor-0.2.2.dist-info/RECORD
