Metadata-Version: 2.1
Name: tauntaun-live-editor
Version: 0.2.2
Summary: Project Tauntaun Live Editor
Home-page: https://github.com/UOAF/project-tauntaun
Author: UOAF
Author-email: uoaf@fakemail.invalid
License: UNKNOWN
Platform: UNKNOWN
Classifier: Programming Language :: Python :: 3.8
Classifier: License :: OSI Approved :: GNU General Public License v3 (GPLv3)
Classifier: Operating System :: OS Independent
Requires-Python: >=3.8
Requires-Dist: Quart (>=0.12.0)
Requires-Dist: dataclasses-json (>=0.5.2)
Requires-Dist: wheel (>=0.35.1)
